matrix/__init__.py
matrix/__version__.py
matrix/exceptions.py
matrix/matrix.py
matrix/utils.py
matrix/components/__init__.py
matrix/components/bases.py
matrix/components/columns.py
matrix/components/elements.py
matrix/components/rows.py
matrix/components/utils.py
matrix_47-0.1.2.dist-info/LICENSE
matrix_47-0.1.2.dist-info/METADATA
matrix_47-0.1.2.dist-info/WHEEL
matrix_47-0.1.2.dist-info/top_level.txt
matrix_47-0.1.2.dist-info/RECORD
