Metadata-Version: 2.1
Name: matrix-47
Version: 0.1.2
Summary: A python package for matrix operations and manipulations.
Home-page: https://github.com/AnonymouX47/matrix
Author: AnonymouX47
Author-email: feyidab01@gmail.com
License: GPLv3.0
Platform: UNKNOWN
Classifier: License :: OSI Approved :: GNU General Public License v3 (GPLv3)
Classifier: Operating System :: OS Independent
Classifier: Programming Language :: Python
Classifier: Programming Language :: Python :: 3
Classifier: Programming Language :: Python :: 3.8
Classifier: Programming Language :: Python :: 3.9
Classifier: Programming Language :: Python :: 3.10
Classifier: Programming Language :: Python :: Implementation :: CPython
Classifier: Topic :: Software Development :: Libraries
Requires-Python: >=3.8
License-File: LICENSE
